openbb_cftc/__init__.py
openbb_cftc/assets/__init__.py
openbb_cftc/assets/cot_ids.json
openbb_cftc/models/__init__.py
openbb_cftc/models/cot.py
openbb_cftc/models/cot_search.py
openbb_cftc/utils/__init__.py
openbb_cftc-1.1.1.dist-info/METADATA
openbb_cftc-1.1.1.dist-info/WHEEL
openbb_cftc-1.1.1.dist-info/entry_points.txt
openbb_cftc-1.1.1.dist-info/RECORD
