Metadata-Version: 2.3
Name: openbb-cftc
Version: 1.1.1
Summary: The mission of the Commodity Futures Trading Commission (CFTC) is to promote the integrity, resilience, and vibrancy of the U.S. derivatives markets through sound regulation.
License: AGPL-3.0-only
Author: OpenBB Team
Author-email: hello@openbb.co
Requires-Python: >=3.9.21,<3.13
Classifier: License :: OSI Approved :: GNU Affero General Public License v3
Classifier: Programming Language :: Python :: 3
Classifier: Programming Language :: Python :: 3.10
Classifier: Programming Language :: Python :: 3.11
Classifier: Programming Language :: Python :: 3.12
Requires-Dist: openbb-core (>=1.4.6,<2.0.0)
